{
  "summary": {
    "totalSales": 12500000,
    "totalOrders": 320,
    "totalCustomers": 210,
    "totalProducts": 85
  },
  "salesTrend": [
    { "month": "Jan", "sales": 1200000 },
    { "month": "Feb", "sales": 1500000 },
    { "month": "Mar", "sales": 1800000 },
    { "month": "Apr", "sales": 2000000 },
    { "month": "May", "sales": 1700000 }
  ],
  "categoryDistribution": [
    { "category": "Electronics", "value": 40 },
    { "category": "Clothing", "value": 25 },
    { "category": "Shoes", "value": 20 },
    { "category": "Accessories", "value": 15 }
  ],
  "topProducts": [
    { "name": "Laptop", "sales": 50 },
    { "name": "T-Shirt", "sales": 80 },
    { "name": "Sneakers", "sales": 65 },
    { "name": "Watch", "sales": 40 }
  ],
  "recentTransactions": [
    {
      "id": 1,
      "customer": "Andi",
      "product": "Laptop",
      "amount": 7000000,
      "date": "2026-03-01"
    },
    {
      "id": 2,
      "customer": "Budi",
      "product": "Sneakers",
      "amount": 900000,
      "date": "2026-03-03"
    },
    {
      "id": 3,
      "customer": "Siti",
      "product": "T-Shirt",
      "amount": 150000,
      "date": "2026-03-05"
    }
  ]
}